{
  "id": 3568,
  "subject": "Replacement part for throttle",
  "description_text": "Hello.      I moved the blue stopper on the throttle to be closer to the pedal, when I accelerated apparently the black tabs that holds the spring that makes force to the load cell, broke.      I need a replacement for both. ",
  "status": 3,
  "priority": 1,
  "created_at": "2025-09-06T20:17:48Z",
  "updated_at": "2025-09-17T09:49:39Z",
  "requester_id": 158004192351,
  "responder_id": 158000445778,
  "cc_emails": [],
  "conversations": [
    {
      "id": 158008196397,
      "body_text": "Hello.\r\n\r\nI logged in and see there's no ticket for me.\r\n\r\nI was able to dig more and find that something broke on my throttle.\r\n\r\nI moved the blue stopped to be closer to the pedal, and apparently this black tab that holds the throttle spring, broke when I pressed the throttle and I need a replacement for this tabs. They are two and both of them broke.\r\n\r\n\r\n\r\n\r\nSent from my T-Mobile 5G Device\r\nGet Outlook for Android<https://aka.ms/AAb9ysg>\r\n________________________________\r\n",
      "user_id": 158004192351,
      "created_at": "2025-09-06T20:14:57Z",
      "updated_at": "2025-09-06T20:14:57Z",
      "incoming": true,
      "private": false,
      "source": 0
    },
    {
      "id": 158008200184,
      "body_text": "Hi Josue Rosa,  Please provide your order number and the model of your pedals, along with the contact person's name, phone number, and address. We will arrange to send you the improved replacement parts tomorrow, Monday. ",
      "user_id": 158000445778,
      "created_at": "2025-09-07T01:19:26Z",
      "updated_at": "2025-09-07T01:19:26Z",
      "incoming": false,
      "private": false,
      "source": 0
    },
    {
      "id": 158008200416,
      "body_text": "Hello.\r\n\r\nI bought these pedals on Amazon, brand new.\r\n\r\nSimsonn Pro X Ultra.\r\n\r\nJosue Rosa\r\n2500 University Ave, Apt 3K\r\nBronx, NY, 10468\r\n\r\n\r\nOrder placed\r\nOrder #\r\nAugust 1, 2025\r\n113-2727781-6709856\r\n\r\n\r\nSent from my T-Mobile 5G Device\r\nGet Outlook for Android<https://aka.ms/AAb9ysg>\r\n________________________________\r\n",
      "user_id": 158004192351,
      "created_at": "2025-09-07T01:39:42Z",
      "updated_at": "2025-09-07T01:39:42Z",
      "incoming": true,
      "private": false,
      "source": 0
    },
    {
      "id": 158008200561,
      "body_text": "ID 为 3529 的工单已合并到此工单。",
      "user_id": 158000445778,
      "created_at": "2025-09-07T01:56:15Z",
      "updated_at": "2025-09-07T01:56:15Z",
      "incoming": false,
      "private": true,
      "source": 2
    },
    {
      "id": 158008200563,
      "body_text": "合并来自工单3529  \n      主题: Question about part  \n      描述:  \nHello.  \n \n \n \n \nI recently purchased the pro x ultra pedals. I was adjusting the stopper in the throttle and after I moved the stopper and pressed the throttle, this part fell down. Now I have an issue with the throttle where it only detects input after ~25% of the pedal is\n pressed.  \n \n \n \n \nSent from my T-Mobile 5G Device \nGet Outlook for Android",
      "user_id": 158000445778,
      "created_at": "2025-09-07T01:56:16Z",
      "updated_at": "2025-09-07T01:56:16Z",
      "incoming": false,
      "private": true,
      "source": 2
    },
    {
      "id": 158008200739,
      "body_text": "Hi Josue Rosa,  We will send you the new parts via express delivery tomorrow. Once they are shipped, we will promptly update you with the tracking number. ",
      "user_id": 158000445778,
      "created_at": "2025-09-07T02:12:27Z",
      "updated_at": "2025-09-07T02:12:27Z",
      "incoming": false,
      "private": false,
      "source": 0
    },
    {
      "id": 158008715082,
      "body_text": "Hello.\r\n\r\nCan you please provide me the tracking number for the part you were supposed to ship on Monday?\r\n\r\nThank you.\r\n\r\nSent from my T-Mobile 5G Device\r\nGet Outlook for Android<https://aka.ms/AAb9ysg>\r\n________________________________\r\n",
      "user_id": 158004192351,
      "created_at": "2025-09-14T22:57:40Z",
      "updated_at": "2025-09-14T22:57:40Z",
      "incoming": true,
      "private": false,
      "source": 0
    },
    {
      "id": 158008716298,
      "body_text": "Hi Josue Rosa,    I’ll check and get back to you with the tracking number shortly. My apologies for forgetting to reply earlier.",
      "user_id": 158000445778,
      "created_at": "2025-09-14T23:52:01Z",
      "updated_at": "2025-09-14T23:52:01Z",
      "incoming": false,
      "private": false,
      "source": 0
    },
    {
      "id": 158008746252,
      "body_text": "Hello?\r\n\r\nCan I please have the tracking number?\r\n\r\nSent from my T-Mobile 5G Device\r\nGet Outlook for Android<https://aka.ms/AAb9ysg>\r\n________________________________\r\n",
      "user_id": 158004192351,
      "created_at": "2025-09-15T11:05:59Z",
      "updated_at": "2025-09-15T11:05:59Z",
      "incoming": true,
      "private": false,
      "source": 0
    },
    {
      "id": 158008851551,
      "body_text": "Hi Josue Rosa,  Here is the tracking number: SF6045919782060. the shipping carrier is SF Express, you can track it via https://www.sf-international.com/cn/en/support/querySupport/waybill",
      "user_id": 158000445778,
      "created_at": "2025-09-17T09:44:52Z",
      "updated_at": "2025-09-17T09:44:52Z",
      "incoming": false,
      "private": false,
      "source": 0
    }
  ]
}