{
  "id": 5527,
  "subject": "simsoon pro",
  "description_text": "hola  como se puede actualizar firmware de la pedalera\r\n\r\n",
  "status": 5,
  "priority": 1,
  "created_at": "2025-11-01T17:55:18Z",
  "updated_at": "2025-11-02T01:47:40Z",
  "requester_id": 158006276774,
  "responder_id": 158000445778,
  "cc_emails": [],
  "conversations": [
    {
      "id": 158011603334,
      "body_text": "此工单已关闭并合并到工单 5521 中",
      "user_id": 158000445778,
      "created_at": "2025-11-02T01:47:40Z",
      "updated_at": "2025-11-02T01:47:40Z",
      "incoming": false,
      "private": true,
      "source": 2
    }
  ]
}